LICENSE.txt
README.md
__init__.py
setup.py
skill.json
version.py
./__init__.py
./skill.json
./version.py
./locale/ca-es/dialog/NotFound.dialog
./locale/ca-es/dialog/YouWillNeed.dialog
./locale/ca-es/vocab/Again.voc
./locale/ca-es/vocab/Ingredients.voc
./locale/ca-es/vocab/Needed.intent
./locale/ca-es/vocab/Recipie.intent
./locale/ca-es/vocab/TellMe.voc
./locale/ca-es/vocab/What.voc
./locale/da-dk/dialog/NotFound.dialog
./locale/da-dk/dialog/YouWillNeed.dialog
./locale/da-dk/vocab/Again.voc
./locale/da-dk/vocab/Ingredients.voc
./locale/da-dk/vocab/Needed.intent
./locale/da-dk/vocab/Recipie.intent
./locale/da-dk/vocab/TellMe.voc
./locale/da-dk/vocab/What.voc
./locale/de-de/dialog/NotFound.dialog
./locale/de-de/dialog/YouWillNeed.dialog
./locale/de-de/vocab/Again.voc
./locale/de-de/vocab/Ingredients.voc
./locale/de-de/vocab/Needed.intent
./locale/de-de/vocab/Recipie.intent
./locale/de-de/vocab/TellMe.voc
./locale/de-de/vocab/What.voc
./locale/el-gr/dialog/NotFound.dialog
./locale/el-gr/dialog/YouWillNeed.dialog
./locale/el-gr/vocab/Again.voc
./locale/el-gr/vocab/Ingredients.voc
./locale/el-gr/vocab/Needed.intent
./locale/el-gr/vocab/Recipie.intent
./locale/el-gr/vocab/TellMe.voc
./locale/el-gr/vocab/What.voc
./locale/en-us/dialog/NotFound.dialog
./locale/en-us/dialog/RandomDrink.dialog
./locale/en-us/dialog/YouWillNeed.dialog
./locale/en-us/vocab/Again.voc
./locale/en-us/vocab/Ingredients.voc
./locale/en-us/vocab/Needed.intent
./locale/en-us/vocab/Random.intent
./locale/en-us/vocab/Recipe.intent
./locale/en-us/vocab/TellMe.voc
./locale/en-us/vocab/What.voc
./locale/es-es/dialog/NotFound.dialog
./locale/es-es/dialog/YouWillNeed.dialog
./locale/es-es/vocab/Again.voc
./locale/es-es/vocab/Ingredients.voc
./locale/es-es/vocab/Needed.intent
./locale/es-es/vocab/Recipie.intent
./locale/es-es/vocab/TellMe.voc
./locale/es-es/vocab/What.voc
./locale/es-lm/dialog/NotFound.dialog
./locale/es-lm/dialog/YouWillNeed.dialog
./locale/es-lm/vocab/Again.voc
skill_cocktail.egg-info/PKG-INFO
skill_cocktail.egg-info/SOURCES.txt
skill_cocktail.egg-info/dependency_links.txt
skill_cocktail.egg-info/entry_points.txt
skill_cocktail.egg-info/requires.txt
skill_cocktail.egg-info/top_level.txt