Metadata-Version: 2.1
Name: skill-cocktail
Version: 0.0.1
Home-page: https://github.com/forslund/skill-cocktail
Author: Åke Forslund
Author-email: ake.forslund@gmail.com
License: GPL
Keywords: ovos skill voice assistant neon
License-File: LICENSE.txt
Requires-Dist: ovos-utils
Requires-Dist: ovos-bus-client
Requires-Dist: ovos-workshop
Requires-Dist: ovos-plugin-manager
